packaging_demo/my_different_file.py
packaging_demo/my_json_data_test.py
packaging_demo/my_other_file.py
packaging_demo/states_info.py
packaging_demo/images/Courses.png
packaging_demo/images/__init__.py
packaging_demo/my_folder/__init__.py
packaging_demo/my_folder/cities.json
packaging_demo/my_folder/my_data.json
packaging_demo_bsahlas-0.0.4.dist-info/METADATA
packaging_demo_bsahlas-0.0.4.dist-info/WHEEL
packaging_demo_bsahlas-0.0.4.dist-info/top_level.txt
packaging_demo_bsahlas-0.0.4.dist-info/RECORD
