Metadata-Version: 2.4
Name: packaging_demo_bsahlas
Version: 0.0.4
Summary: udemy.com - TPP Course working with PyPI
Author: Bill Sahlas
Author-email: bill.sahlas@gmail.com
License-Expression: MIT
Project-URL: homepage, https://example.com
Project-URL: documentation, https://readthedocs.org
Project-URL: repository, https://github.com/bsahlas/packaging-demo
Keywords: tpp,continuous delivery,python
Classifier: Programming Language :: Python
Requires-Python: >=3.8
Requires-Dist: numpy
Requires-Dist: fastapi
Provides-Extra: colors
Requires-Dist: rich; extra == "colors"
Provides-Extra: static-code-analysis
Requires-Dist: pre-commit; extra == "static-code-analysis"
Provides-Extra: test
Requires-Dist: pytest; extra == "test"
Requires-Dist: pytest-cov; extra == "test"
Provides-Extra: release
Requires-Dist: twine; extra == "release"
Requires-Dist: build; extra == "release"
Provides-Extra: dev
Requires-Dist: packaging-demo[colors,release,static-code-analysis,test]; extra == "dev"
